dagi/__init__.py
dagi-0.1.0.dist-info/LICENSE
dagi-0.1.0.dist-info/METADATA
dagi-0.1.0.dist-info/WHEEL
dagi-0.1.0.dist-info/top_level.txt
dagi-0.1.0.dist-info/RECORD
